README.rst
setup.py
hftools/__init__.py
hftools.egg-info/PKG-INFO
hftools.egg-info/SOURCES.txt
hftools.egg-info/dependency_links.txt
hftools.egg-info/entry_points.txt
hftools.egg-info/requires.txt
hftools.egg-info/top_level.txt
hftools/fitting/__init__.py
hftools/hepdata/__init__.py
hftools/hepdata/rootcnv/__init__.py
hftools/hepdata/rootcnv/cli.py
hftools/hepdata/rootcnv/formatters.py
hftools/jupyter/__init__.py
hftools/plotting/__init__.py
hftools/plotting/quickplot_cli.py
hftools/utils/__init__.py
hftools/utils/parsexml.py