Metadata-Version: 1.0
Name: hftools
Version: 0.0.6
Summary: simple tools to extract to do post-processing on HistFactory configurations / workspaces (e.g. extract data for HepData, simple stacked plots etc.)
Home-page: UNKNOWN
Author: Lukas Heinrich
Author-email: lukas.heinrich@cern.ch
License: UNKNOWN
Platform: UNKNOWN
